{
  "questions": [
    {
      "stage": "pre",
      "question": "adjacency matrix の A[i][j] = 1 は何を表しますか。",
      "options": [
        "node i の degree が j である",
        "node i から node j への edge がある",
        "node i と node j が同じ label を持つ",
        "i から j への shortest path の長さが 1 である"
      ],
      "correct": 1,
      "explanation": "adjacency matrix はグラフの中心的表現です。A[i][j] = 1 は node i と node j を結ぶ edge があることを意味します。無向グラフでは A[i][j] = A[j][i] です。"
    },
    {
      "stage": "pre",
      "question": "BFS はどの data structure を使い、何を見つけますか。",
      "options": [
        "Stack。connected components を見つける",
        "Queue。無重みグラフの shortest paths を見つける",
        "Priority queue。minimum spanning tree を見つける",
        "Hash map。duplicate nodes を見つける"
      ],
      "correct": 1,
      "explanation": "BFS は queue (FIFO) を使い、距離 k の neighbor をすべて探索してから距離 k+1 に進みます。最初に発見された経路が source からの shortest path です。"
    },
    {
      "stage": "post",
      "question": "connected graph の graph Laplacian L = D - A には、ゼロ固有値がいくつありますか。",
      "options": [
        "ゼロ個",
        "ちょうど一つ",
        "node 数と同じ",
        "edge 数と同じ"
      ],
      "correct": 1,
      "explanation": "Laplacian のゼロ固有値の個数は connected components の個数に等しいです。connected graph は component が一つなので、ゼロ固有値はちょうど一つです。"
    },
    {
      "stage": "post",
      "question": "GNN message passing の h_v^(k+1) = sigma(W * mean({h_u^(k) : u in neighbors(v)})) は何を計算しますか。",
      "options": [
        "v から全 node への shortest path",
        "neighbor features を集約し、learned weights で変換し、非線形性を適用した node v の新しい feature vector",
        "layer k+1 における node v の degree",
        "node v の PageRank score"
      ],
      "correct": 1,
      "explanation": "各 node は neighbor の features を集め、平均で aggregate し、weight matrix W と activation sigma で新しい表現を作ります。k rounds 後には k-hop neighborhood の情報を持ちます。"
    },
    {
      "stage": "post",
      "question": "spectral clustering は Fiedler vector (L の二番目に小さい固有値の eigenvector) をどのように使いますか。",
      "options": [
        "Fiedler vector の最大 entries を持つ node が一つの cluster になる",
        "Fiedler vector の値が正の node を一方、負の node を他方に分ける",
        "Fiedler vector を edge weights として使う",
        "Fiedler vector が cluster 数を決める"
      ],
      "correct": 1,
      "explanation": "Fiedler vector はグラフ上の非自明で最も滑らかな関数を表します。同じ密な cluster の node は似た値を持ち、bottleneck で分かれた node は反対符号になりやすいです。"
    }
  ]
}
